Metadata-Version: 2.1
Name: opty
Version: 1.3.0
Summary: Tool for optimizing dynamic systems using direct collocation.
Home-page: http://github.com/csu-hmc/opty
Author: Jason K. Moore
Author-email: moorepants@gmail.com
License: BSD-2-clause
Classifier: Programming Language :: Python
Classifier: Programming Language :: Python :: 3.8
Classifier: Programming Language :: Python :: 3.9
Classifier: Programming Language :: Python :: 3.10
Classifier: Programming Language :: Python :: 3.11
Classifier: Programming Language :: Python :: 3.12
Classifier: Operating System :: OS Independent
Classifier: Development Status :: 5 - Production/Stable
Classifier: Intended Audience :: Science/Research
Classifier: License :: OSI Approved :: BSD License
Classifier: Natural Language :: English
Classifier: Topic :: Scientific/Engineering
Classifier: Topic :: Scientific/Engineering :: Physics
License-File: LICENSE
License-File: AUTHORS
Requires-Dist: cyipopt>=1.1.0
Requires-Dist: cython>=0.29.19
Requires-Dist: numpy>=1.19.0
Requires-Dist: scipy>=1.5.0
Requires-Dist: sympy>=1.6.0
Provides-Extra: examples
Requires-Dist: matplotlib>=3.2.0; extra == "examples"
Requires-Dist: pandas; extra == "examples"
Requires-Dist: pydy>=0.5.0; extra == "examples"
Requires-Dist: tables; extra == "examples"
Requires-Dist: yeadon; extra == "examples"
Provides-Extra: doc
Requires-Dist: numpydoc; extra == "doc"
Requires-Dist: sphinx; extra == "doc"
Requires-Dist: sphinx-gallery; extra == "doc"
